llama_index/packs/trulens_eval_packs/__init__.py
llama_index/packs/trulens_eval_packs/base.py
llama_index_packs_trulens_eval_packs-0.4.1.dist-info/METADATA
llama_index_packs_trulens_eval_packs-0.4.1.dist-info/WHEEL
llama_index_packs_trulens_eval_packs-0.4.1.dist-info/licenses/LICENSE
llama_index_packs_trulens_eval_packs-0.4.1.dist-info/RECORD
