Metadata-Version: 2.4
Name: llama-index-packs-trulens-eval-packs
Version: 0.4.1
Summary: llama-index packs trulens_eval_packs integration
Author-email: Your Name <you@example.com>
Maintainer: joshreini1
License-Expression: MIT
License-File: LICENSE
Keywords: eval,harmless,helpful,rag,triad,trulens
Requires-Python: >=3.9
Requires-Dist: llama-index-core<0.15,>=0.13.0
Requires-Dist: trulens-eval<0.22,>=0.21.0
